thejsonlogger/__init__.py
thejsonlogger/thejsonlogger.py
thejsonlogger-0.0.3.dist-info/LICENSE
thejsonlogger-0.0.3.dist-info/METADATA
thejsonlogger-0.0.3.dist-info/WHEEL
thejsonlogger-0.0.3.dist-info/top_level.txt
thejsonlogger-0.0.3.dist-info/RECORD
