Metadata-Version: 2.1
Name: thejsonlogger
Version: 0.0.3
Summary: The JSON Logger
Home-page: https://github.com/rueth-io/thejsonlogger
Author: Aaron Rueth
Author-email: Aaron Rueth <arueth@gmail.com>
Project-URL: Homepage, https://github.com/rueth-io/my-json-logger
Project-URL: Issues, https://github.com/rueth-io/my-json-logger/issues
Classifier: License :: OSI Approved :: Apache Software License
Classifier: Operating System :: OS Independent
Classifier: Programming Language :: Python :: 3
Classifier: Topic :: System :: Logging
Requires-Python: >=3.8
License-File: LICENSE
